pybancointer/__init__.py
pybancointer/script.js
pybancointer-0.0.1.dist-info/LICENSE
pybancointer-0.0.1.dist-info/WHEEL
pybancointer-0.0.1.dist-info/METADATA
pybancointer-0.0.1.dist-info/RECORD
