Metadata-Version: 2.1
Name: pybancointer
Version: 0.0.1
Summary: This module do web crawler of banco inter.
Home-page: https://github.com/guifabrin/pybancointer
Author: Guilherme Fabrin Franco
Author-email: guilherme.fabrin@gmail.com
Classifier: License :: OSI Approved :: MIT License
